MANIFEST.in
setup.py
pombo_correio/__init__.py
pombo_correio/exceptions.py
pombo_correio/utils.py
pombo_correio.egg-info/PKG-INFO
pombo_correio.egg-info/SOURCES.txt
pombo_correio.egg-info/dependency_links.txt
pombo_correio.egg-info/top_level.txt
pombo_correio/__pycache__/__init__.cpython-38.pyc
pombo_correio/__pycache__/exceptions.cpython-38.pyc
pombo_correio/__pycache__/utils.cpython-38.pyc
pombo_correio/res/prefs.js
pombo_correio/res/extensions/@testpilot-containers.xpi
pombo_correio/res/extensions/CanvasBlocker@kkapsner.de.xpi
pombo_correio/res/extensions/CookieAutoDelete@kennydo.com.xpi
pombo_correio/res/extensions/https-everywhere@eff.org.xpi
pombo_correio/res/extensions/jid1-BoFifL9Vbdl2zQ@jetpack.xpi
pombo_correio/res/extensions/jid1-MnnxcxisBPnSXQ@jetpack.xpi
pombo_correio/res/extensions/uBlock0@raymondhill.net.xpi
pombo_correio/res/extensions/uMatrix@raymondhill.net.xpi
pombo_correio/res/extensions/{74145f27-f039-47ce-a470-a662b129930a}.xpi
pombo_correio/res/extensions/{c607c8df-14a7-4f28-894f-29e8722976af}.xpi