Metadata-Version: 1.0
Name: pombo-correio
Version: 0.2.1
Summary: simple selenium wrapper
Home-page: https://github.com/JarbasAl/pombo_correio
Author: jarbasAI
Author-email: jarbasai@mailfence.com
License: Apache
Platform: UNKNOWN
